django_admin_logentry_extension/__init__.py
django_admin_logentry_extension/admin.py
django_admin_logentry_extension/apps.py
django_admin_logentry_extension/models.py
django_admin_logentry_extension/monkey.py
django_admin_logentry_extension/tests.py
django_admin_logentry_extension/utils.py
django_admin_logentry_extension/views.py
django_admin_logentry_extension/migrations/__init__.py
django_admin_logentry_extension-0.1.4.dist-info/licenses/LICENSE
django_admin_logentry_extension-0.1.4.dist-info/METADATA
django_admin_logentry_extension-0.1.4.dist-info/WHEEL
django_admin_logentry_extension-0.1.4.dist-info/top_level.txt
django_admin_logentry_extension-0.1.4.dist-info/RECORD
